README.md
setup.py
Py2PostgreS/Py2SQL.py
Py2PostgreS/__init__.py
Py2PostgreS.egg-info/PKG-INFO
Py2PostgreS.egg-info/SOURCES.txt
Py2PostgreS.egg-info/dependency_links.txt
Py2PostgreS.egg-info/not-zip-safe
Py2PostgreS.egg-info/requires.txt
Py2PostgreS.egg-info/top_level.txt