Metadata-Version: 1.0
Name: Py2PostgreS
Version: 0.8.0.2
Summary: Py to postgreSQL
Home-page: UNKNOWN
Author: Blahyi Andrii, Kushnirenko Mariia, Tochanenko Vladislav, Velychko Taisiia
Author-email: blagij00@gmail.com
License: MIT
Platform: UNKNOWN
